pdr_sapphire_wrapper-0.1.12.data/data/sapphire_wrapper_bin/sapphirewrapper.dylib
pdr_sapphire_wrapper-0.1.12.data/data/sapphire_wrapper_bin/sapphirewrapper.so
sapphire_wrapper/__init__.py
sapphire_wrapper/wrapper.py
pdr_sapphire_wrapper-0.1.12.dist-info/LICENSE
pdr_sapphire_wrapper-0.1.12.dist-info/METADATA
pdr_sapphire_wrapper-0.1.12.dist-info/WHEEL
pdr_sapphire_wrapper-0.1.12.dist-info/top_level.txt
pdr_sapphire_wrapper-0.1.12.dist-info/RECORD
