Metadata-Version: 2.1
Name: pdr-sapphire-wrapper
Version: 0.1.12
Summary: Sapphire transaction wrapper
Home-page: https://github.com/oceanprotocol/pdr-sapphire-wrapper
Author: oceanprotocol
Author-email: devops@oceanprotocol.com
License: Apache Software License 2.0
Classifier: Development Status :: 2 - Pre-Alpha
Classifier: Intended Audience :: Developers
Classifier: License :: OSI Approved :: Apache Software License
Classifier: Natural Language :: English
Classifier: Programming Language :: Python :: 3.8
License-File: LICENSE
